hma17.py
hma17-0.0.2.dist-info/entry_points.txt
hma17-0.0.2.dist-info/LICENSE
hma17-0.0.2.dist-info/WHEEL
hma17-0.0.2.dist-info/METADATA
hma17-0.0.2.dist-info/RECORD
