Metadata-Version: 2.1
Name: hma17
Version: 0.0.2
Summary: this is a program that just says hello michelle
Home-page: https://github.com/Carreau/hma17
License: UNKNOWN
Author: Matthias Bussonnier
Author-email: mbussonnier@ucmerced.edu
Classifier: License :: OSI Approved :: MIT License
